uva_luyanfei/__about__.py
uva_luyanfei/__init__.py
uva_luyanfei/cli.py
uva_luyanfei/data/pid-to-num.cvs
uva_luyanfei-0.1.1.dist-info/METADATA
uva_luyanfei-0.1.1.dist-info/WHEEL
uva_luyanfei-0.1.1.dist-info/entry_points.txt
uva_luyanfei-0.1.1.dist-info/licenses/LICENSE.txt
uva_luyanfei-0.1.1.dist-info/RECORD
