Metadata-Version: 2.4
Name: uva-luyanfei
Version: 0.1.1
Project-URL: Documentation, https://github.com/luyanfei/uva#readme
Project-URL: Issues, https://github.com/luyanfei/uva/issues
Project-URL: Source, https://github.com/luyanfei/uva
Author-email: luyanfei <luyanfei78@163.com>
License-Expression: MIT
License-File: LICENSE.txt
Classifier: Development Status :: 4 - Beta
Classifier: Programming Language :: Python
Classifier: Programming Language :: Python :: 3.8
Classifier: Programming Language :: Python :: 3.9
Classifier: Programming Language :: Python :: 3.10
Classifier: Programming Language :: Python :: 3.11
Classifier: Programming Language :: Python :: 3.12
Classifier: Programming Language :: Python :: Implementation :: CPython
Classifier: Programming Language :: Python :: Implementation :: PyPy
Requires-Python: >=3.8
Requires-Dist: bs4
Requires-Dist: click
